{"generation": 15, "best": [true, true, true, true, true, true, true, true, true, false, true, true, false, true, false, true, false, false, false, true, true, false, true, true, true, true, true, true, false, false, false, false, true, false, true, true, false, false, false, false, false, true, true, false, false, true, true, true, true, true, false, false, true, true, false, false, false, true, true, true, true, false, false, true, false, false, false, false, false, false, false, false, false, false, false, false, false, true, false, false, false, true, false, true, false, true, false, false, true, true, false, false, true, true, false, true, false, true, true, true], "config": {"tournament-size": 2, "crossover-prob": 0.75, "replacement": true, "idle-generations": 5, "rand-gen-prob": 0.5, "report-delta": 1, "pack-size": 517, "stochastic-prob": 0.9, "population-size": 10, "max-generations": 100, "name": "amanas: simple - tournament 2 - run 7"}, "status": [["Generation", "Fitness"], [1, 1654.17], [2, 1654.17], [3, 1666.62], [4, 1666.62], [5, 1709.64], [6, 1709.64], [7, 1709.64], [8, 1709.64], [9, 1746], [10, 1746], [11, 1788.86], [12, 1788.86], [13, 1788.86], [14, 1788.86], [15, 1788.86], [15, 1788.86]], "start-time": 1481467851359, "current-time": 1481467855369, "result": "Done! Too many generations without improving fitness", "best-decoded": [{"ratio": 28.40584415584416, "val": 87.49, "vol": 3.08, "nam": "object 39"}, {"ratio": 23.42537313432836, "val": 94.17, "vol": 4.02, "nam": "object 44"}, {"ratio": 21.53768844221106, "val": 42.86, "vol": 1.99, "nam": "object 32"}, {"ratio": 16.29185520361991, "val": 72.01, "vol": 4.42, "nam": "object 83"}, {"ratio": 15.97627737226277, "val": 87.55, "vol": 5.48, "nam": "object 72"}, {"ratio": 13.22871452420701, "val": 79.24, "vol": 5.99, "nam": "object 77"}, {"ratio": 12.22769640479361, "val": 91.83, "vol": 7.51, "nam": "object 25"}, {"ratio": 11.06310013717421, "val": 80.65, "vol": 7.29, "nam": "object 38"}, {"ratio": 7.694805194805195, "val": 23.7, "vol": 3.08, "nam": "object 81"}, {"ratio": 5.743697478991597, "val": 82.02, "vol": 14.28, "nam": "object 64"}, {"ratio": 5.272574312955693, "val": 94.01, "vol": 17.83, "nam": "object 21"}, {"ratio": 4.936233611442193, "val": 82.83, "vol": 16.78, "nam": "object 9"}, {"ratio": 4.097791798107256, "val": 38.97, "vol": 9.51, "nam": "object 46"}, {"ratio": 3.188757396449704, "val": 53.89, "vol": 16.9, "nam": "object 0"}, {"ratio": 3.166043380703067, "val": 84.66, "vol": 26.74, "nam": "object 23"}, {"ratio": 2.990392313851081, "val": 74.7, "vol": 24.98, "nam": "object 12"}, {"ratio": 2.780387770320656, "val": 74.57, "vol": 26.82, "nam": "object 15"}, {"ratio": 2.755688622754491, "val": 46.02, "vol": 16.7, "nam": "object 61"}, {"ratio": 2.663377192982456, "val": 24.29, "vol": 9.12, "nam": "object 42"}, {"ratio": 2.455399061032864, "val": 52.3, "vol": 21.3, "nam": "object 31"}, {"ratio": 2.089964580873672, "val": 88.51, "vol": 42.35, "nam": "object 92"}, {"ratio": 1.639156469669357, "val": 62.96, "vol": 38.41, "nam": "object 56"}, {"ratio": 1.545184025058731, "val": 98.66, "vol": 63.85, "nam": "object 97"}, {"ratio": 1.493547197640118, "val": 81.01, "vol": 54.24, "nam": "object 55"}, {"ratio": 1.271519434628975, "val": 89.96, "vol": 70.75, "nam": "object 73"}], "best-volume": 513.42, "best-fitness": 1788.86}